{
  "$schema": "https://developer.microsoft.com/json-schemas/fabric/item/report/definition/visualContainer/2.10.0/schema.json",
  "name": "grafico_concepto_onpe",
  "position": {
    "x": 576.30644567219156,
    "y": 225.2925721301412,
    "z": 6000,
    "height": 236.35604665438919,
    "width": 637.65844076120322,
    "tabOrder": 6000
  },
  "visual": {
    "visualType": "clusteredBarChart",
    "query": {
      "queryState": {
        "Category": {
          "projections": [
            {
              "field": {
                "Column": {
                  "Expression": {
                    "SourceRef": {
                      "Entity": "ONPE_GastosCampana"
                    }
                  },
                  "Property": "Concepto"
                }
              },
              "queryRef": "ONPE_GastosCampana.Concepto",
              "nativeQueryRef": "Concepto",
              "active": true
            }
          ]
        },
        "Y": {
          "projections": [
            {
              "field": {
                "Aggregation": {
                  "Expression": {
                    "Column": {
                      "Expression": {
                        "SourceRef": {
                          "Entity": "ONPE_GastosCampana"
                        }
                      },
                      "Property": "Monto"
                    }
                  },
                  "Function": 0
                }
              },
              "queryRef": "Sum(ONPE_GastosCampana.Monto)",
              "nativeQueryRef": "Monto"
            }
          ]
        }
      }
    },
    "objects": {
      "dataPoint": [
        {
          "properties": {
            "fill": {
              "solid": {
                "color": {
                  "expr": {
                    "ThemeDataColor": {
                      "ColorId": 9,
                      "Percent": 0.2
                    }
                  }
                }
              }
            }
          }
        }
      ]
    },
    "visualContainerObjects": {
      "title": [
        {
          "properties": {
            "show": {
              "expr": {
                "Literal": {
                  "Value": "true"
                }
              }
            },
            "text": {
              "expr": {
                "Literal": {
                  "Value": "'Monto por concepto reportado'"
                }
              }
            }
          }
        }
      ]
    },
    "drillFilterOtherVisuals": true
  }
}